.gitignore
LICENSE
MANIFEST.in
README.md
generate_modules.bat
img.jpg
img.psd
jetbrains.svg
readthedocs.yml
requirements.txt
setup.py
upload.bat
.idea/.gitignore
.idea/deployment.xml
.idea/fastgplearn.iml
.idea/misc.xml
.idea/modules.xml
.idea/vcs.xml
.idea/inspectionProfiles/profiles_settings.xml
Instance/simple_sample.py
bin/mgetool
docs/Install.rst
docs/Introduction.rst
docs/Makefile
docs/Readme
docs/conf.py
docs/contact.rst
docs/generate_modules.bat
docs/img.jpg
docs/index.rst
docs/jetbrains.svg
docs/make.bat
docs/requirements.txt
docs/ustbgjj.png
docs/Examples/baseclf.rst
docs/Examples/basereg.rst
docs/Examples/index.rst
docs/Guide/Graph1.png
docs/Guide/Graph2.png
docs/Guide/Graph3.png
docs/Guide/benchmark.rst
docs/Guide/index.rst
docs/Guide/pards.rst
docs/Guide/sci_template.rst
docs/Guide/with_t.png
docs/Guide/without_t.png
docs/src/fastgplearn.backend.rst
docs/src/fastgplearn.cli.rst
docs/src/fastgplearn.rst
docs/src/modules.rst
fastgplearn/README.md
fastgplearn/__init__.py
fastgplearn/gp.py
fastgplearn/sci_formula.py
fastgplearn/skflow.py
fastgplearn/tools.py
fastgplearn.egg-info/PKG-INFO
fastgplearn.egg-info/SOURCES.txt
fastgplearn.egg-info/dependency_links.txt
fastgplearn.egg-info/entry_points.txt
fastgplearn.egg-info/requires.txt
fastgplearn.egg-info/top_level.txt
fastgplearn/backend/__init__.py
fastgplearn/backend/c_numpy.py
fastgplearn/backend/c_torch.py
fastgplearn/backend/p_numpy.py
fastgplearn/backend/p_torch.py
fastgplearn/cli/__init__.py
fastgplearn/cli/cc_numpy.py
fastgplearn/cli/cc_torch.py
fastgplearn/cli/main.py
fastgplearn/source/np_tool.pyx
fastgplearn/source/torch_tool.cpp
inst/badk.py
inst/tte_time.py
inst/tte_time2.py
inst/tte_timeclf.py
test/gd.py
test/test_classi_general.py
test/test_regressor_general.py
test/test_sci_sub.py