Metadata-Version: 2.1
Name: fastgplearn
Version: 0.0.17
Summary: Fast fitting formula.
Home-page: https://github.com/boliqq07/fastgplearn
Author: wangchangxin
Author-email: 986798607@qq.com
Maintainer: wangchangxin
Keywords: genetic programming","symbolic learning
Classifier: Development Status :: 4 - Beta
Classifier: Intended Audience :: Science/Research
Classifier: License :: OSI Approved :: MIT License
Classifier: Natural Language :: English
Classifier: Programming Language :: Python :: 3.6
Classifier: Programming Language :: Python :: 3.7
Classifier: Programming Language :: Python :: 3.8
Classifier: Programming Language :: Python :: 3.9
Requires-Python: >=3.6
License-File: LICENSE
